[
  {
    "symbol": "SOLUSDT",
    "side": "LONG",
    "size": 2.51,
    "entryPrice": 0.0,
    "unrealizedPnl": 0.62413805,
    "openedAt": "2025-11-25T19:24:03+08:00",
    "reportedAt": "2025-11-25T20:06:15+08:00"
  },
  {
    "symbol": "ETHUSDT",
    "side": "LONG",
    "size": 0.079,
    "entryPrice": 0.0,
    "unrealizedPnl": 0.34931289,
    "openedAt": "2025-11-25T19:24:02+08:00",
    "reportedAt": "2025-11-25T20:06:15+08:00"
  },
  {
    "symbol": "BTCUSDT",
    "side": "LONG",
    "size": 0.004,
    "entryPrice": 0.0,
    "unrealizedPnl": 1.89050524,
    "openedAt": "2025-11-25T19:24:02+08:00",
    "reportedAt": "2025-11-25T20:06:15+08:00"
  }
]