[
  {
    "symbol": "BNBUSDT",
    "side": "LONG",
    "size": 0.36,
    "entryPrice": 0.0,
    "unrealizedPnl": -0.9684,
    "openedAt": "2025-11-22T03:30:15+08:00",
    "reportedAt": "2025-11-22T03:35:39+08:00"
  },
  {
    "symbol": "XRPUSDT",
    "side": "LONG",
    "size": 201.8,
    "entryPrice": 0.0,
    "unrealizedPnl": -1.60407187,
    "openedAt": "2025-11-22T03:30:14+08:00",
    "reportedAt": "2025-11-22T03:35:39+08:00"
  },
  {
    "symbol": "BTCUSDT",
    "side": "LONG",
    "size": 0.003,
    "entryPrice": 0.0,
    "unrealizedPnl": -0.78717789,
    "openedAt": "2025-11-22T03:30:15+08:00",
    "reportedAt": "2025-11-22T03:35:39+08:00"
  }
]