[
  {
    "symbol": "SOLUSDT",
    "side": "LONG",
    "size": 1.52,
    "entryPrice": 0.0,
    "unrealizedPnl": -1.0944,
    "openedAt": "2025-11-22T15:53:02+08:00",
    "reportedAt": "2025-11-22T17:38:13+08:00"
  },
  {
    "symbol": "ETHUSDT",
    "side": "LONG",
    "size": 0.105,
    "entryPrice": 0.0,
    "unrealizedPnl": -2.3268,
    "openedAt": "2025-11-22T15:53:02+08:00",
    "reportedAt": "2025-11-22T17:38:13+08:00"
  },
  {
    "symbol": "BTCUSDT",
    "side": "LONG",
    "size": 0.004,
    "entryPrice": 0.0,
    "unrealizedPnl": -1.59902914,
    "openedAt": "2025-11-22T15:53:01+08:00",
    "reportedAt": "2025-11-22T17:38:13+08:00"
  }
]