[
  {
    "symbol": "SOLUSDT",
    "side": "LONG",
    "size": 1.32,
    "entryPrice": 0.0,
    "unrealizedPnl": -1.82058705,
    "openedAt": "2025-11-23T13:10:08+08:00",
    "reportedAt": "2025-11-23T14:51:53+08:00"
  },
  {
    "symbol": "ETHUSDT",
    "side": "LONG",
    "size": 0.024,
    "entryPrice": 0.0,
    "unrealizedPnl": -0.37248,
    "openedAt": "2025-11-23T13:10:08+08:00",
    "reportedAt": "2025-11-23T14:51:53+08:00"
  },
  {
    "symbol": "BNBUSDT",
    "side": "LONG",
    "size": 0.1,
    "entryPrice": 0.0,
    "unrealizedPnl": -0.413,
    "openedAt": "2025-11-23T13:10:09+08:00",
    "reportedAt": "2025-11-23T14:51:53+08:00"
  },
  {
    "symbol": "DOGEUSDT",
    "side": "LONG",
    "size": 1158.0,
    "entryPrice": 0.0,
    "unrealizedPnl": -0.62000478,
    "openedAt": "2025-11-23T13:10:08+08:00",
    "reportedAt": "2025-11-23T14:51:53+08:00"
  },
  {
    "symbol": "XRPUSDT",
    "side": "LONG",
    "size": 174.5,
    "entryPrice": 0.0,
    "unrealizedPnl": -3.04752907,
    "openedAt": "2025-11-23T13:10:08+08:00",
    "reportedAt": "2025-11-23T14:51:53+08:00"
  }
]